lightcone_io/__init__.py
lightcone_io/choose_bh_tracer.py
lightcone_io/combine_maps.py
lightcone_io/compare_maps.py
lightcone_io/correct_maps.py
lightcone_io/downsample_maps.py
lightcone_io/halo_catalogue.py
lightcone_io/halo_reader.py
lightcone_io/healpix_maps.py
lightcone_io/index_particles.py
lightcone_io/kernel.py
lightcone_io/match_black_holes.py
lightcone_io/memory_use.py
lightcone_io/particle_halo_ids.py
lightcone_io/particle_metadata.py
lightcone_io/particle_reader.py
lightcone_io/particle_sorter.py
lightcone_io/smoothed_map.py
lightcone_io/units.py
lightcone_io/util.py
lightcone_io-0.4.0.dist-info/METADATA
lightcone_io-0.4.0.dist-info/WHEEL
lightcone_io-0.4.0.dist-info/top_level.txt
lightcone_io-0.4.0.dist-info/RECORD
