Metadata-Version: 2.4
Name: lightcone_io
Version: 0.4.0
Summary: Module for reading SWIFT lightcone output.
Author-email: John Helly <j.c.helly@durham.ac.uk>
Project-URL: Homepage, https://github.com/jchelly/LightconeIO
Project-URL: Repository, https://github.com/jchelly/LightconeIO.git
Project-URL: Issues, https://github.com/jchelly/LightconeIO/issues
Classifier: Programming Language :: Python :: 3
Classifier: License :: OSI Approved :: GNU General Public License v3 (GPLv3)
Classifier: Operating System :: OS Independent
Requires-Python: >=3.10
Requires-Dist: h5py
Requires-Dist: numpy
Requires-Dist: unyt
Requires-Dist: healpy
Requires-Dist: scipy
Requires-Dist: tqdm
Provides-Extra: mpi
Requires-Dist: mpi4py; extra == "mpi"
Requires-Dist: virgodc>=1.0.1; extra == "mpi"
